{
  "main": {
    "id": "8528909487a475b5",
    "type": "split",
    "children": [
      {
        "id": "57da07c7907dd305",
        "type": "tabs",
        "children": [
          {
            "id": "e147c8221965df61",
            "type": "leaf",
            "state": {
              "type": "markdown",
              "state": {
                "file": "Selected Topics Lecture 8.md",
                "mode": "source",
                "backlinks": false,
                "source": false
              }
            }
          },
          {
            "id": "2a2a6e79602715ee",
            "type": "leaf",
            "state": {
              "type": "markdown",
              "state": {
                "file": "Selected Topics Lecture 9.md",
                "mode": "source",
                "backlinks": false,
                "source": false
              }
            }
          }
        ],
        "currentTab": 1
      }
    ],
    "direction": "vertical"
  },
  "left": {
    "id": "b94a83590bcd25bf",
    "type": "split",
    "children": [
      {
        "id": "0148acad21e90442",
        "type": "tabs",
        "dimension": 72.20779220779221,
        "children": [
          {
            "id": "e969bf01bb468d78",
            "type": "leaf",
            "state": {
              "type": "markdown",
              "state": {
                "file": "Robotics Embeddded Robotics.md",
                "mode": "source",
                "backlinks": false,
                "source": false
              }
            }
          },
          {
            "id": "ed18b9a69b47b3c1",
            "type": "leaf",
            "state": {
              "type": "file-explorer",
              "state": {
                "sortOrder": "alphabetical"
              }
            }
          },
          {
            "id": "987d868666980711",
            "type": "leaf",
            "state": {
              "type": "search",
              "state": {
                "query": "",
                "matchingCase": false,
                "explainSearch": false,
                "collapseAll": false,
                "extraContext": false,
                "sortOrder": "alphabetical"
              }
            }
          },
          {
            "id": "85540f2f847125de",
            "type": "leaf",
            "state": {
              "type": "empty",
              "state": {}
            }
          },
          {
            "id": "55747e47609377d3",
            "type": "leaf",
            "state": {
              "type": "tag",
              "state": {
                "sortOrder": "frequency",
                "useHierarchy": true
              }
            }
          },
          {
            "id": "360f2338552d44fa",
            "type": "leaf",
            "state": {
              "type": "bookmarks",
              "state": {}
            }
          }
        ],
        "currentTab": 1
      },
      {
        "id": "577b64fe7f784a7f",
        "type": "tabs",
        "dimension": 27.792207792207797,
        "children": [
          {
            "id": "8b2531ed8a72c9f5",
            "type": "leaf",
            "state": {
              "type": "outline",
              "state": {
                "file": "Selected Topics Lecture 9.md"
              }
            }
          },
          {
            "id": "66b47dc96de0f5a0",
            "type": "leaf",
            "state": {
              "type": "outgoing-link",
              "state": {
                "file": "Selected Topics Lecture 9.md",
                "linksCollapsed": false,
                "unlinkedCollapsed": true
              }
            }
          },
          {
            "id": "2390bde648ad1f36",
            "type": "leaf",
            "state": {
              "type": "backlink",
              "state": {
                "file": "Selected Topics Lecture 9.md",
                "collapseAll": false,
                "extraContext": false,
                "sortOrder": "alphabetical",
                "showSearch": false,
                "searchQuery": "",
                "backlinkCollapsed": false,
                "unlinkedCollapsed": true
              }
            }
          }
        ]
      }
    ],
    "direction": "horizontal",
    "width": 303.5
  },
  "right": {
    "id": "1b03d21cf79103db",
    "type": "split",
    "children": [],
    "direction": "horizontal",
    "width": 200,
    "collapsed": true
  },
  "left-ribbon": {
    "hiddenItems": {
      "graph:Open graph view": false,
      "random-note:Open random note": false,
      "templater-obsidian:Templater": false,
      "auto-moc:AutoMOC": false,
      "janitor:Janitor: scan vault": false,
      "periodic-notes:Open today": false
    }
  },
  "active": "2a2a6e79602715ee",
  "lastOpenFiles": [
    "Selected Topics Lecture 8.md",
    "Selected Topics Lecture 9.md",
    "Robotics Actuators 1.md",
    "Robotics Sensors 2.md",
    "Selected Topics Lecture 6.md",
    "Robotics Embeddded Robotics.md",
    "Day Planners/Day Planner-20230503.md",
    "Day Planners",
    "Robotics Sensors 1.md",
    "Robotics Robot Behavior.md",
    "Robotics Actuators 2.md",
    "Selected Topics Lecture 4.md",
    "Selected Topics Lecture 3.md",
    "Selected Topics Lecture 2.md",
    "Selected Topics Lecture 5.md",
    "Selected Topics Lecture 1.md",
    "VR Week 1.md",
    "Pasted image 20230427235942.png",
    "02 Sources/JS Timeouts and Intervals.md",
    "02 Sources/JS.md",
    "02 Sources/JS Dates & Internationalization.md",
    "04 Calendars/Logs/2023.md",
    "04 Calendars/Logs/2023-03-20.md",
    "04 Calendars/Logs/2023-04-16.md",
    "02 Sources/JS Numbers & Math.md",
    "02 Sources/JS Types.md",
    "02 Sources/JS Strings.md",
    "02 Sources/JS Maps.md",
    "05 Extras/Attachments/Pasted image 20230411004203.png",
    "05 Extras/Attachments/Pasted image 20230323131156.png",
    "05 Extras/Attachments/Pasted image 20230323131029 1.png",
    "05 Extras/Attachments/Pasted image 20230323131029.png",
    "04"
  ]
}